README.md
ss_test/__init__.py
ss_test/console/application.py
ss_test/sample_size.py
ss_test-0.0.1a8.dist-info/entry_points.txt
ss_test-0.0.1a8.dist-info/WHEEL
ss_test-0.0.1a8.dist-info/METADATA
ss_test-0.0.1a8.dist-info/RECORD
