Metadata-Version: 2.1
Name: ss-test
Version: 0.0.1a8
Summary: A python module just to test publish
Keywords: test
Maintainer: WendyChiang
Maintainer-email: wendypjchiang@gmail.com
Requires-Python: >=3.7.1,<3.11
Classifier: Programming Language :: Python :: 3
Classifier: Programming Language :: Python :: 3.10
Classifier: Programming Language :: Python :: 3.8
Classifier: Programming Language :: Python :: 3.9
Requires-Dist: statsmodels (>=0.13.1,<0.14.0)
